{
  "train_config": {
    "model": "LSTM",
    "dataset_environment_str": "RTX2080Ti_CPUALL",
    "meta_dataset_environment_strs": ["RTX2080Ti_CPUALL"],
    "dataset_subgraph_node_size": 12,
    "dataset_subgraph_step": 2,
    "all_seed": 42,
    "dataset_params": {
      "duration_summed": false
    },
    "model_params": {
      "num_layers": 4,
      "bidirectional": true
    },
    "dataset_dummy": true,
    "batch_size": 128,
    "eval_steps": 5000,
    "learning_rate": 0.001,
    "epochs": 100,
    "optimizer": "Adam",
    "meta_configs": {
      "learning_rate": 0.005,
      "meta_learning_rate": 0.001,
      "meta_train_steps": 1000,
      "meta_task_per_step": 8,
      "meta_fast_adaption_step": 5,
      "meta_dataset_train_environment_strs": ["RTX2080Ti_CPUALL"],
      "meta_dataset_eval_environment_strs": ["RTX2080Ti_CPUALL"]
    }
  },
  "train_records": {
    "loss": [],
    "eval_metrics": [
      {
        "metrics": {
          "eval_loss": 0.11621797681046822,
          "MRE": 1.884267762501261,
          "MAE": 1.0507297479830113,
          "RMSE": 671.27141333269,
          "train_loss": 0.1621353030204773
        },
        "step": 0,
        "duration": 0.113996562
      },
      {
        "metrics": {
          "eval_loss": 0.01481084265675967,
          "MRE": 0.08282158209392097,
          "MAE": 0.102553963921015,
          "RMSE": 195.28618517053556,
          "train_loss": 0.019118305295705795
        },
        "step": 5000,
        "duration": 22.399802077
      },
      {
        "metrics": {
          "eval_loss": 0.01134586100205215,
          "MRE": 0.06836196973084749,
          "MAE": 0.06953477242729504,
          "RMSE": 125.21278543429898,
          "train_loss": 0.011813638731837273
        },
        "step": 10000,
        "duration": 44.609355492
      },
      {
        "metrics": {
          "eval_loss": 0.009950010957779632,
          "MRE": 0.06648617260428417,
          "MAE": 0.06273563394746244,
          "RMSE": 105.24338032444857,
          "train_loss": 0.006224212236702442
        },
        "step": 15000,
        "duration": 66.469630375
      },
      {
        "metrics": {
          "eval_loss": 0.008757189348713284,
          "MRE": 0.060049047469147444,
          "MAE": 0.06073994684335247,
          "RMSE": 105.25749564505763,
          "train_loss": 0.005848153959959745
        },
        "step": 20000,
        "duration": 88.811670494
      },
      {
        "metrics": {
          "eval_loss": 0.008112537412633868,
          "MRE": 0.06159238625332038,
          "MAE": 0.053833352477888216,
          "RMSE": 85.61790626048304,
          "train_loss": 0.006994024850428104
        },
        "step": 25000,
        "duration": 111.307072232
      },
      {
        "metrics": {
          "eval_loss": 0.007410021959116158,
          "MRE": 0.05836145548470051,
          "MAE": 0.052016244849675375,
          "RMSE": 79.27005927891628,
          "train_loss": 0.005993489176034927
        },
        "step": 30000,
        "duration": 133.942787807
      },
      {
        "metrics": {
          "eval_loss": 0.007163503259548212,
          "MRE": 0.05983673321604591,
          "MAE": 0.0514835297357362,
          "RMSE": 67.64799322994894,
          "train_loss": 0.0064782146364450455
        },
        "step": 35000,
        "duration": 156.727272313
      },
      {
        "metrics": {
          "eval_loss": 0.007877695243073551,
          "MRE": 0.05655372581253898,
          "MAE": 0.05508382760628589,
          "RMSE": 88.95333464758552,
          "train_loss": 0.005534987896680832
        },
        "step": 40000,
        "duration": 179.35346676
      },
      {
        "metrics": {
          "eval_loss": 0.006355853382665748,
          "MRE": 0.05328053117525699,
          "MAE": 0.04661494679655089,
          "RMSE": 69.46180435857487,
          "train_loss": 0.00609439006075263
        },
        "step": 45000,
        "duration": 202.050469264
      },
      {
        "metrics": {
          "eval_loss": 0.006511908367550878,
          "MRE": 0.04982275221002266,
          "MAE": 0.038542042937876726,
          "RMSE": 49.75973134038725,
          "train_loss": 0.005188852548599243
        },
        "step": 50000,
        "duration": 224.922144522
      },
      {
        "metrics": {
          "eval_loss": 0.006392084759691269,
          "MRE": 0.05213390598185949,
          "MAE": 0.04100598059328414,
          "RMSE": 54.84335689969838,
          "train_loss": 0.005712047219276428
        },
        "step": 55000,
        "duration": 247.660671182
      },
      {
        "metrics": {
          "eval_loss": 0.006289645308439953,
          "MRE": 0.058052600392995354,
          "MAE": 0.046923159626012144,
          "RMSE": 55.852586049173155,
          "train_loss": 0.005115099251270294
        },
        "step": 60000,
        "duration": 270.060929423
      },
      {
        "metrics": {
          "eval_loss": 0.005753807292834252,
          "MRE": 0.050081110657775124,
          "MAE": 0.03851512525169558,
          "RMSE": 51.290720765752205,
          "train_loss": 0.005079919472336769
        },
        "step": 65000,
        "duration": 292.230220893
      },
      {
        "metrics": {
          "eval_loss": 0.005661995852147511,
          "MRE": 0.05177257884228671,
          "MAE": 0.03952322053571612,
          "RMSE": 47.6954053979265,
          "train_loss": 0.00801309384405613
        },
        "step": 70000,
        "duration": 314.440623465
      },
      {
        "metrics": {
          "eval_loss": 0.005937291071456185,
          "MRE": 0.05025164142827492,
          "MAE": 0.043175581688967034,
          "RMSE": 57.53840802613367,
          "train_loss": 0.005617201328277588
        },
        "step": 75000,
        "duration": 336.62395761
      },
      {
        "metrics": {
          "eval_loss": 0.005388578289657556,
          "MRE": 0.05031493838129622,
          "MAE": 0.037827422197140796,
          "RMSE": 46.079285198268515,
          "train_loss": 0.004728472791612148
        },
        "step": 80000,
        "duration": 361.840977042
      },
      {
        "metrics": {
          "eval_loss": 0.005504295136421374,
          "MRE": 0.04775073088804743,
          "MAE": 0.03744916448760734,
          "RMSE": 44.36540104508783,
          "train_loss": 0.00485377898439765
        },
        "step": 85000,
        "duration": 384.637715668
      },
      {
        "metrics": {
          "eval_loss": 0.005390268150165998,
          "MRE": 0.045408264885783985,
          "MAE": 0.035089057602569196,
          "RMSE": 42.97898068817793,
          "train_loss": 0.0051791551522910595
        },
        "step": 90000,
        "duration": 407.488096977
      },
      {
        "metrics": {
          "eval_loss": 0.0052805150315592625,
          "MRE": 0.04843024291577202,
          "MAE": 0.039688660976129414,
          "RMSE": 46.5203244992525,
          "train_loss": 0.0046931966207921505
        },
        "step": 95000,
        "duration": 430.283787709
      },
      {
        "metrics": {
          "eval_loss": 0.005239402409249133,
          "MRE": 0.049147110681726607,
          "MAE": 0.038341853334340814,
          "RMSE": 43.8729190944353,
          "train_loss": 0.005786102265119553
        },
        "step": 100000,
        "duration": 453.01764166
      },
      {
        "metrics": {
          "eval_loss": 0.005252067758604979,
          "MRE": 0.04723251079657357,
          "MAE": 0.036799747662755844,
          "RMSE": 39.14420369191064,
          "train_loss": 0.004644900560379028
        },
        "step": 105000,
        "duration": 475.377354649
      },
      {
        "metrics": {
          "eval_loss": 0.005070381090150739,
          "MRE": 0.04546812072843788,
          "MAE": 0.034311165185979695,
          "RMSE": 38.74730263861348,
          "train_loss": 0.052286889404058456
        },
        "step": 110000,
        "duration": 497.485505739
      },
      {
        "metrics": {
          "eval_loss": 0.00507109201647761,
          "MRE": 0.0468063048385485,
          "MAE": 0.035903807550755514,
          "RMSE": 36.81096872079339,
          "train_loss": 0.004430519416928291
        },
        "step": 115000,
        "duration": 519.708528973
      },
      {
        "metrics": {
          "eval_loss": 0.00511663900729171,
          "MRE": 0.04869479954347626,
          "MAE": 0.03413356330485463,
          "RMSE": 32.52898790190172,
          "train_loss": 0.0042180996388196945
        },
        "step": 120000,
        "duration": 542.064636457
      },
      {
        "metrics": {
          "eval_loss": 0.0050776723096017115,
          "MRE": 0.04523636574225807,
          "MAE": 0.03475613954596397,
          "RMSE": 35.75770001120816,
          "train_loss": 0.004191933199763298
        },
        "step": 125000,
        "duration": 564.44344715
      },
      {
        "metrics": {
          "eval_loss": 0.0049685111474544325,
          "MRE": 0.04886127414770757,
          "MAE": 0.03765357718200256,
          "RMSE": 36.11463539821456,
          "train_loss": 0.004317862447351217
        },
        "step": 130000,
        "duration": 586.751699831
      },
      {
        "metrics": {
          "eval_loss": 0.004881383290096695,
          "MRE": 0.044912435255546154,
          "MAE": 0.03601813469488932,
          "RMSE": 38.33171198177672,
          "train_loss": 0.004632947966456413
        },
        "step": 135000,
        "duration": 609.154286007
      },
      {
        "metrics": {
          "eval_loss": 0.0048234614079080635,
          "MRE": 0.04494326262697718,
          "MAE": 0.03452759912255865,
          "RMSE": 32.91549561496837,
          "train_loss": 0.004572109319269657
        },
        "step": 140000,
        "duration": 631.589183301
      },
      {
        "metrics": {
          "eval_loss": 0.005051420963392263,
          "MRE": 0.04564137658617938,
          "MAE": 0.034836797121949856,
          "RMSE": 39.382756605484985,
          "train_loss": 0.0046048215590417385
        },
        "step": 145000,
        "duration": 654.416747978
      },
      {
        "metrics": {
          "eval_loss": 0.004797197995207377,
          "MRE": 0.04501050145789952,
          "MAE": 0.03353264605980103,
          "RMSE": 31.688939316306943,
          "train_loss": 0.0034195068292319775
        },
        "step": 150000,
        "duration": 676.721913737
      },
      {
        "metrics": {
          "eval_loss": 0.004796377345386289,
          "MRE": 0.04691519095857566,
          "MAE": 0.035992720113996325,
          "RMSE": 32.866826398289426,
          "train_loss": 0.003951977472752333
        },
        "step": 155000,
        "duration": 699.150086612
      },
      {
        "metrics": {
          "eval_loss": 0.004651925546605741,
          "MRE": 0.042427793767593855,
          "MAE": 0.030452657655238517,
          "RMSE": 29.764614631651874,
          "train_loss": 0.0045953793451189995
        },
        "step": 160000,
        "duration": 724.830779133
      },
      {
        "metrics": {
          "eval_loss": 0.004605224478246342,
          "MRE": 0.04505306470269537,
          "MAE": 0.03236197784618912,
          "RMSE": 27.286431596182048,
          "train_loss": 0.003987056203186512
        },
        "step": 165000,
        "duration": 747.572246894
      },
      {
        "metrics": {
          "eval_loss": 0.004706551302173391,
          "MRE": 0.04487955090430388,
          "MAE": 0.03298090568320324,
          "RMSE": 30.229218718963047,
          "train_loss": 0.004259052686393261
        },
        "step": 170000,
        "duration": 770.382607433
      },
      {
        "metrics": {
          "eval_loss": 0.004552740024824818,
          "MRE": 0.04325808969071784,
          "MAE": 0.031069970015926006,
          "RMSE": 29.109704702094678,
          "train_loss": 0.004078317433595657
        },
        "step": 175000,
        "duration": 793.230412535
      },
      {
        "metrics": {
          "eval_loss": 0.004461005020838803,
          "MRE": 0.0449953507923108,
          "MAE": 0.032030259823430204,
          "RMSE": 26.985021454838307,
          "train_loss": 0.003687361953780055
        },
        "step": 180000,
        "duration": 815.945367398
      },
      {
        "metrics": {
          "eval_loss": 0.0043621062171594754,
          "MRE": 0.04330056067271039,
          "MAE": 0.029295072462007465,
          "RMSE": 26.297358829657295,
          "train_loss": 0.0044794040732085705
        },
        "step": 185000,
        "duration": 838.66369734
      },
      {
        "metrics": {
          "eval_loss": 0.004400429344059376,
          "MRE": 0.04577053971380449,
          "MAE": 0.032253521805474444,
          "RMSE": 26.887996111079605,
          "train_loss": 0.004488397855311632
        },
        "step": 190000,
        "duration": 861.397705388
      },
      {
        "metrics": {
          "eval_loss": 0.004375411552217949,
          "MRE": 0.04385805524082987,
          "MAE": 0.031664422225147607,
          "RMSE": 25.101624343175434,
          "train_loss": 0.003956899978220463
        },
        "step": 195000,
        "duration": 884.214039766
      },
      {
        "metrics": {
          "eval_loss": 0.004214164336433934,
          "MRE": 0.04374783698145161,
          "MAE": 0.029693291834142037,
          "RMSE": 24.644266686137673,
          "train_loss": 0.004353866912424564
        },
        "step": 200000,
        "duration": 906.726775489
      },
      {
        "metrics": {
          "eval_loss": 0.004392983633014288,
          "MRE": 0.041406445200630214,
          "MAE": 0.028029775924954117,
          "RMSE": 24.69142202691761,
          "train_loss": 0.004437081050127745
        },
        "step": 205000,
        "duration": 929.468488156
      },
      {
        "metrics": {
          "eval_loss": 0.0042271896241594,
          "MRE": 0.04474520289756532,
          "MAE": 0.031455225519884514,
          "RMSE": 25.2222511485657,
          "train_loss": 0.0032839798368513584
        },
        "step": 210000,
        "duration": 952.364040366
      },
      {
        "metrics": {
          "eval_loss": 0.004716089299436885,
          "MRE": 0.04216027094044165,
          "MAE": 0.028372407749464396,
          "RMSE": 24.91181570602975,
          "train_loss": 0.003991955891251564
        },
        "step": 215000,
        "duration": 975.234608986
      },
      {
        "metrics": {
          "eval_loss": 0.004235011601737177,
          "MRE": 0.041606851516668826,
          "MAE": 0.02708180281847687,
          "RMSE": 24.14322957862213,
          "train_loss": 0.0038168723694980145
        },
        "step": 220000,
        "duration": 998.123720957
      },
      {
        "metrics": {
          "eval_loss": 0.004207097223059595,
          "MRE": 0.04030393894719683,
          "MAE": 0.027410271962413496,
          "RMSE": 24.55597602497551,
          "train_loss": 0.0032553996425122023
        },
        "step": 225000,
        "duration": 1020.930801951
      },
      {
        "metrics": {
          "eval_loss": 0.004159073889578516,
          "MRE": 0.04375542846607341,
          "MAE": 0.030869224604699718,
          "RMSE": 25.221605049270213,
          "train_loss": 0.003958560526371002
        },
        "step": 230000,
        "duration": 1046.648849213
      },
      {
        "metrics": {
          "eval_loss": 0.004199187573961813,
          "MRE": 0.040976697791692135,
          "MAE": 0.02812051628949776,
          "RMSE": 24.340714714531096,
          "train_loss": 0.00442168116569519
        },
        "step": 235000,
        "duration": 1069.738909485
      },
      {
        "metrics": {
          "eval_loss": 0.004036764702983212,
          "MRE": 0.04116595933917014,
          "MAE": 0.028866101548723586,
          "RMSE": 24.885381921595247,
          "train_loss": 0.004353443160653114
        },
        "step": 240000,
        "duration": 1092.479734995
      },
      {
        "metrics": {
          "eval_loss": 0.004320862316011905,
          "MRE": 0.03875254810561062,
          "MAE": 0.027213588863391574,
          "RMSE": 24.108329726775533,
          "train_loss": 0.004024553578346968
        },
        "step": 245000,
        "duration": 1114.94684041
      },
      {
        "metrics": {
          "eval_loss": 0.004336615247263308,
          "MRE": 0.04158850639435284,
          "MAE": 0.028475995998835248,
          "RMSE": 23.92146904946353,
          "train_loss": 0.004334026947617531
        },
        "step": 250000,
        "duration": 1137.337259201
      },
      {
        "metrics": {
          "eval_loss": 0.00413935216016098,
          "MRE": 0.04008151602946162,
          "MAE": 0.028557923456428488,
          "RMSE": 24.603475920596335,
          "train_loss": 0.003955583553761244
        },
        "step": 255000,
        "duration": 1159.527623372
      },
      {
        "metrics": {
          "eval_loss": 0.004346512003956884,
          "MRE": 0.0441194126882579,
          "MAE": 0.03249300115440848,
          "RMSE": 27.054369788892014,
          "train_loss": 0.004858542699366808
        },
        "step": 260000,
        "duration": 1182.082945804
      },
      {
        "metrics": {
          "eval_loss": 0.004048764472855444,
          "MRE": 0.04192720526980834,
          "MAE": 0.02945648355313126,
          "RMSE": 24.767912595721306,
          "train_loss": 0.0032583842985332012
        },
        "step": 265000,
        "duration": 1204.118524874
      },
      {
        "metrics": {
          "eval_loss": 0.004106064839809911,
          "MRE": 0.038762453476250555,
          "MAE": 0.027071859787145956,
          "RMSE": 22.363013540520942,
          "train_loss": 0.004217496141791344
        },
        "step": 270000,
        "duration": 1226.563379775
      },
      {
        "metrics": {
          "eval_loss": 0.004176571695032031,
          "MRE": 0.04448887161804399,
          "MAE": 0.02874203045766267,
          "RMSE": 23.574148554560296,
          "train_loss": 0.0049260882660746574
        },
        "step": 275000,
        "duration": 1249.117088848
      },
      {
        "metrics": {
          "eval_loss": 0.003990106889497988,
          "MRE": 0.04023836380282187,
          "MAE": 0.02789285502993397,
          "RMSE": 24.460975362653755,
          "train_loss": 0.004549158271402121
        },
        "step": 280000,
        "duration": 1271.761178411
      },
      {
        "metrics": {
          "eval_loss": 0.004190082342917129,
          "MRE": 0.045279309575298306,
          "MAE": 0.03251148163313205,
          "RMSE": 26.662766015293663,
          "train_loss": 0.003782826941460371
        },
        "step": 285000,
        "duration": 1294.278923738
      },
      {
        "metrics": {
          "eval_loss": 0.004520450973575055,
          "MRE": 0.04397449031577918,
          "MAE": 0.03225117839776393,
          "RMSE": 28.69904990585056,
          "train_loss": 0.0040192073211073875
        },
        "step": 290000,
        "duration": 1316.899740965
      },
      {
        "metrics": {
          "eval_loss": 0.004292273633818133,
          "MRE": 0.04285134188658828,
          "MAE": 0.031446118297967375,
          "RMSE": 28.646089159884834,
          "train_loss": 0.0038674785755574703
        },
        "step": 295000,
        "duration": 1339.490433798
      },
      {
        "metrics": {
          "eval_loss": 0.004287011937664182,
          "MRE": 0.041127583252216764,
          "MAE": 0.030715057319039188,
          "RMSE": 27.25402240163102,
          "train_loss": 0.0038721091113984585
        },
        "step": 300000,
        "duration": 1361.799412822
      },
      {
        "metrics": {
          "eval_loss": 0.004298989558658823,
          "MRE": 0.041702287476033884,
          "MAE": 0.029977963329972268,
          "RMSE": 25.435313623186378,
          "train_loss": 0.004221081733703613
        },
        "step": 305000,
        "duration": 1387.54643923
      },
      {
        "metrics": {
          "eval_loss": 0.003998749122063638,
          "MRE": 0.042293963380779814,
          "MAE": 0.029122053312913097,
          "RMSE": 23.350530182322,
          "train_loss": 0.003353916807100177
        },
        "step": 310000,
        "duration": 1410.539056483
      },
      {
        "metrics": {
          "eval_loss": 0.004095587877576897,
          "MRE": 0.03974776587613501,
          "MAE": 0.027600664559202747,
          "RMSE": 23.103795490326146,
          "train_loss": 0.0046727703884243965
        },
        "step": 315000,
        "duration": 1433.446677591
      },
      {
        "metrics": {
          "eval_loss": 0.004016716749836483,
          "MRE": 0.03964210480207391,
          "MAE": 0.02764289254251362,
          "RMSE": 22.93358626777454,
          "train_loss": 0.004045305773615837
        },
        "step": 320000,
        "duration": 1455.694207759
      },
      {
        "metrics": {
          "eval_loss": 0.0039951985065891146,
          "MRE": 0.04001047137734424,
          "MAE": 0.026474497646060857,
          "RMSE": 22.172815066694728,
          "train_loss": 0.004693320952355862
        },
        "step": 325000,
        "duration": 1478.149712183
      },
      {
        "metrics": {
          "eval_loss": 0.0040852812614043475,
          "MRE": 0.04192975586171296,
          "MAE": 0.029408580016708073,
          "RMSE": 24.99556066845905,
          "train_loss": 0.3271166682243347
        },
        "step": 330000,
        "duration": 1501.22431075
      },
      {
        "metrics": {
          "eval_loss": 0.003945800311598338,
          "MRE": 0.0407756117867507,
          "MAE": 0.028540273768328028,
          "RMSE": 24.165676634441706,
          "train_loss": 0.0035062532406300306
        },
        "step": 335000,
        "duration": 1524.328093687
      },
      {
        "metrics": {
          "eval_loss": 0.003990624860401197,
          "MRE": 0.04376430746084772,
          "MAE": 0.03077841785568449,
          "RMSE": 24.17388079821386,
          "train_loss": 0.0035316734574735165
        },
        "step": 340000,
        "duration": 1547.533889118
      },
      {
        "metrics": {
          "eval_loss": 0.004048708170839089,
          "MRE": 0.04283058671896097,
          "MAE": 0.028777076889516376,
          "RMSE": 24.933854997194675,
          "train_loss": 0.004482448101043701
        },
        "step": 345000,
        "duration": 1570.382080535
      },
      {
        "metrics": {
          "eval_loss": 0.0039048786314281447,
          "MRE": 0.03892925444091427,
          "MAE": 0.02737323853965861,
          "RMSE": 23.23812916784232,
          "train_loss": 0.004007982090115547
        },
        "step": 350000,
        "duration": 1592.998275193
      },
      {
        "metrics": {
          "eval_loss": 0.003949035103556225,
          "MRE": 0.04145778878472504,
          "MAE": 0.028302617297827504,
          "RMSE": 23.47077338389089,
          "train_loss": 0.004015208221971989
        },
        "step": 355000,
        "duration": 1615.552046481
      },
      {
        "metrics": {
          "eval_loss": 0.0039026381605582012,
          "MRE": 0.038824445848929044,
          "MAE": 0.028236985077691172,
          "RMSE": 23.443670880596784,
          "train_loss": 0.0033835042268037796
        },
        "step": 360000,
        "duration": 1638.109931808
      },
      {
        "metrics": {
          "eval_loss": 0.00391965712143931,
          "MRE": 0.034671264726706796,
          "MAE": 0.02670470729290606,
          "RMSE": 22.22280321038392,
          "train_loss": 0.003472942393273115
        },
        "step": 365000,
        "duration": 1660.958833989
      },
      {
        "metrics": {
          "eval_loss": 0.004046013717653323,
          "MRE": 0.0388606464604455,
          "MAE": 0.027521765109645085,
          "RMSE": 23.98151645175023,
          "train_loss": 0.003409871831536293
        },
        "step": 370000,
        "duration": 1683.734104665
      },
      {
        "metrics": {
          "eval_loss": 0.003967220752520475,
          "MRE": 0.04305987284859649,
          "MAE": 0.03022102420605111,
          "RMSE": 24.813988003488863,
          "train_loss": 0.003085584146901965
        },
        "step": 375000,
        "duration": 1706.840008988
      },
      {
        "metrics": {
          "eval_loss": 0.003940654654488566,
          "MRE": 0.038822108316222285,
          "MAE": 0.0270227949720844,
          "RMSE": 22.598264586114485,
          "train_loss": 0.003727076342329383
        },
        "step": 380000,
        "duration": 1730.055530966
      },
      {
        "metrics": {
          "eval_loss": 0.003926459832908541,
          "MRE": 0.03894051730125379,
          "MAE": 0.02852859790308643,
          "RMSE": 24.437572348135326,
          "train_loss": 0.003371721599251032
        },
        "step": 385000,
        "duration": 1756.024552539
      }
    ]
  }
}
